README.rst
setup.py
esios/__init__.py
esios/archives.py
esios/indicators.py
esios/parsers.py
esios/service.py
esios/utils.py
esios.egg-info/PKG-INFO
esios.egg-info/SOURCES.txt
esios.egg-info/dependency_links.txt
esios.egg-info/requires.txt
esios.egg-info/top_level.txt
esios/data/P48-esios-MP.xsd
esios/data/P48Cierre-esios-MP.xsd
esios/data/esios-code-lists.xsd
esios/data/esios-core-cmpts.xsd
esios/data/urn-sios-ree-es-code-lists.xsd
esios/data/urn-sios-ree-es-core-cmpts.xsd
esios/data/urn-sios-ree-es-p48-1-0.xsd
esios/data/urn-sios-ree-es-p48cierre-1-0.xsd