Metadata-Version: 1.0
Name: esios
Version: 0.26.0
Summary: Interact with e.sios API
Home-page: https://github.com/gisce/esios
Author: GISCE-TI, S.L.
Author-email: devel@gisce.net
License: MIT
Platform: UNKNOWN
